pydantic_cidoc_crm/__init__.py
pydantic_cidoc_crm/abstract_basemodel.py
pydantic_cidoc_crm/cidoc_crm.py
pydantic_cidoc_crm/mapping.py
pydantic_cidoc_crm-0.0.2.dist-info/WHEEL
pydantic_cidoc_crm-0.0.2.dist-info/METADATA
pydantic_cidoc_crm-0.0.2.dist-info/RECORD
