Metadata-Version: 2.1
Name: pydantic_cidoc_crm
Version: 0.0.2
Summary: Pydantic Cidoc-CRM implementation
Home-page: https://github.com/jonasengelmann/pydantic-cidoc-crm
Author: Jonas Engelmann
Author-email: jonas.engelmann@protonmail.com
Requires-Python: >=3.6.1
Classifier: Operating System :: OS Independent
Classifier: Programming Language :: Python :: 3
Classifier: Topic :: Software Development :: Libraries :: Python Modules
Classifier: Topic :: Software Development :: Libraries
Classifier: Topic :: Software Development
Classifier: Development Status :: 4 - Beta
Classifier: License :: OSI Approved :: MIT License
Requires-Dist: pydantic
Requires-Dist: rdflib
Requires-Dist: pre-commit==2.20.0 ; extra == "dev"
Project-URL: Documentation, https://github.com/jonasengelmann/pydantic-cidoc-crm
Provides-Extra: dev
